{"cameraMode":{"drawMode":0,"name":"Shaded","section":"Shading Mode"},"sceneLighting":true,"audioPlay":false,"sceneViewState":{"showFog":true,"showMaterialUpdate":false,"showSkybox":true,"showFlares":true,"showImageEffects":true,"showParticleSystems":true},"in2DMode":false,"pivot":{"x":35.73229217529297,"y":-32.693851470947269,"z":80.92140197753906},"rotation":{"x":-0.1799604594707489,"y":-0.1565551906824112,"z":0.029022105038166047,"w":-0.9707058668136597},"size":62.95097732543945,"orthographic":false}